FPGA_project/Task3/combinedTasks/combinedTasks.srcs/sources_1/new/toPS2.v
`timescale 1ns / 1ps

module toPS2(
    input wire [5:0] coordinates,
    output reg [15:0] PS2coordinates
);
////////////////////////////////Overview//////////////////////////////////////////////

// this module converts a m,n (in binary) into PS2 format for display

wire [2:0] m,n;

assign m = coordinates[5:3];
assign n = coordinates[2:0];
    
always @(*) begin
		case(m)
			3'd1 : PS2coordinates[15:8] = 8'h16; // 1
			3'd2 : PS2coordinates[15:8] = 8'h1E; // 2
			3'd3 : PS2coordinates[15:8] = 8'h26; // 3
			3'd4 : PS2coordinates[15:8] = 8'h25; // 4
			3'd5 : PS2coordinates[15:8] = 8'h2E; // 5
			default : PS2coordinates[15:8] = 8'h00; 
		endcase
end

always @(*) begin
		case(n)
			3'd1 : PS2coordinates[7:0] = 8'h16; // 1
			3'd2 : PS2coordinates[7:0] = 8'h1E; // 2
			3'd3 : PS2coordinates[7:0] = 8'h26; // 3
			3'd4 : PS2coordinates[7:0] = 8'h25; // 4
			3'd5 : PS2coordinates[7:0] = 8'h2E; // 5
			default : PS2coordinates[7:0] = 8'h00;
		endcase
end



endmodule

FPGA_project/Task3/combinedTasks/combinedTasks.srcs/sim_1/new/toPS2_tb.v
`timescale 1ns / 1ps

module tb_toPS2();
    // Inputs
    reg [5:0] coordinates;
    
    // Outputs
    wire [15:0] PS2coordinates;
    
    // Instantiate the Unit Under Test (UUT)
    toPS2 uut (
        .coordinates(coordinates),
        .PS2coordinates(PS2coordinates)
    );
    
    // Test vectors
    initial begin
        // Initialize inputs
        coordinates = 6'b000000;
        
        // Display header
        $display("Time\tm\tn\tPS2coordinates");
        $display("----------------------------------");
        
        // Wait for global reset
        #10;
        
        // Test case 1: m=1, n=1
        coordinates = 6'b001001;
        #10;
        $display("%0t\t%0d\t%0d\t0x%h", $time, coordinates[5:3], coordinates[2:0], PS2coordinates);
        
        // Test case 2: m=2, n=3
        coordinates = 6'b010011;
        #10;
        $display("%0t\t%0d\t%0d\t0x%h", $time, coordinates[5:3], coordinates[2:0], PS2coordinates);
        
        // Test case 3: m=3, n=4
        coordinates = 6'b011100;
        #10;
        $display("%0t\t%0d\t%0d\t0x%h", $time, coordinates[5:3], coordinates[2:0], PS2coordinates);
        
        // Test case 4: m=4, n=5
        coordinates = 6'b100101;
        #10;
        $display("%0t\t%0d\t%0d\t0x%h", $time, coordinates[5:3], coordinates[2:0], PS2coordinates);
        
        // Test case 5: m=5, n=2
        coordinates = 6'b101010;
        #10;
        $display("%0t\t%0d\t%0d\t0x%h", $time, coordinates[5:3], coordinates[2:0], PS2coordinates);
        
        // Test case 6: Invalid m (0), valid n (3)
        coordinates = 6'b000011;
        #10;
        $display("%0t\t%0d\t%0d\t0x%h", $time, coordinates[5:3], coordinates[2:0], PS2coordinates);
        
        // Test case 7: Valid m (5), invalid n (0)
        coordinates = 6'b101000;
        #10;
        $display("%0t\t%0d\t%0d\t0x%h", $time, coordinates[5:3], coordinates[2:0], PS2coordinates);
        
        // Test case 8: Invalid m (6), invalid n (6)
        coordinates = 6'b110110;
        #10;
        $display("%0t\t%0d\t%0d\t0x%h", $time, coordinates[5:3], coordinates[2:0], PS2coordinates);
        
        // End simulation
        #10;
        $finish;
    end
    
    // Optional: Add waveform generation
    initial begin
        $dumpfile("tb_toPS2.vcd");
        $dumpvars(0, tb_toPS2);
    end
endmodule

FPGA_project/Task3/combinedTasks/combinedTasks.sim/sim_1/behav/xsim/tb_toPS2.vcd
$date
   Sun Apr 13 14:04:52 2025
$end

$version
  2024.2.0
  $dumpfile ("tb_toPS2.vcd") 
$end

$timescale
  1ps
$end

$scope module tb_toPS2 $end
$var reg 6 ! coordinates [5:0] $end
$var wire 16 " PS2coordinates [15:0] $end
$scope module uut $end
$var wire 6 # coordinates [5:0] $end
$var reg 16 $ PS2coordinates [15:0] $end
$var wire 3 % m [2:0] $end
$var wire 3 & n [2:0] $end
$upscope $end
$upscope $end
$enddefinitions $end

#0
$dumpvars
b0 !
b0 "
b0 #
b0 $
b0 %
b0 &
$end

#10000
b1001 !
b1011000010110 "
b1001 #
b1011000010110 $
b1 %
b1 &

#20000
b10011 !
b1111000100110 "
b10011 #
b1111000100110 $
b10 %
b11 &

#30000
b11100 !
b10011000100101 "
b11100 #
b10011000100101 $
b11 %
b100 &

#40000
b100101 !
b10010100101110 "
b100101 #
b10010100101110 $
b100 %
b101 &

#50000
b101010 !
b10111000011110 "
b101010 #
b10111000011110 $
b101 %
b10 &

#60000
b11 !
b100110 "
b11 #
b100110 $
b0 %
b11 &

#70000
b101000 !
b10111000000000 "
b101000 #
b10111000000000 $
b101 %
b0 &
